ass2lrc/__init__.py
ass2lrc/ass_converter.py
ass2lrc/cli.py
ass2lrc/converter.py
ass2lrc/expander.py
ass2lrc/lrc_parser.py
ass2lrc/models.py
ass2lrc/parser.py
ass_to_lrc-0.4.0.dist-info/METADATA
ass_to_lrc-0.4.0.dist-info/WHEEL
ass_to_lrc-0.4.0.dist-info/entry_points.txt
ass_to_lrc-0.4.0.dist-info/licenses/LICENSE
ass_to_lrc-0.4.0.dist-info/RECORD
