Metadata-Version: 2.4
Name: ass-to-lrc
Version: 0.4.0
Summary: Convert ASS subtitle files to LRC lyrics format with karaoke timing support
Project-URL: Homepage, https://github.com/nattadasu/ass-to-lrc
Project-URL: Repository, https://github.com/nattadasu/ass-to-lrc
Project-URL: Issues, https://github.com/nattadasu/ass-to-lrc/issues
Project-URL: Documentation, https://github.com/nattadasu/ass-to-lrc#readme
Author-email: Natsu Tadama <nattadasu@nattadasu.my.id>
License: MIT
License-File: LICENSE
Keywords: ass,converter,karaoke,lrc,lyrics,subtitle
Classifier: Development Status :: 4 - Beta
Classifier: Intended Audience :: Developers
Classifier: Intended Audience :: End Users/Desktop
Classifier: License :: OSI Approved :: MIT License
Classifier: Programming Language :: Python :: 3
Classifier: Programming Language :: Python :: 3.11
Classifier: Programming Language :: Python :: 3.12
Classifier: Programming Language :: Python :: 3.13
Classifier: Topic :: Multimedia :: Sound/Audio
Classifier: Topic :: Text Processing
Classifier: Topic :: Utilities
Requires-Python: >=3.11
Requires-Dist: ass>=1.0.3
Requires-Dist: typer>=0.20.0
Provides-Extra: dev
Requires-Dist: hatchling>=1.21.0; extra == 'dev'
Requires-Dist: mypy>=1.0.0; extra == 'dev'
Requires-Dist: pre-commit>=3.6.0; extra == 'dev'
Requires-Dist: pytest-cov>=4.0.0; extra == 'dev'
Requires-Dist: pytest>=7.0.0; extra == 'dev'
Requires-Dist: ruff>=0.1.0; extra == 'dev'
